pymuonsuite/__init__.py
pymuonsuite/constants.py
pymuonsuite/muairss.py
pymuonsuite/optional.py
pymuonsuite/schemas.py
pymuonsuite/symmetry.py
pymuonsuite/utils.py
pymuonsuite/calculate/__init__.py
pymuonsuite/calculate/hfine.py
pymuonsuite/calculate/uep/__init__.py
pymuonsuite/calculate/uep/__main__.py
pymuonsuite/calculate/uep/charged.py
pymuonsuite/data/__init__.py
pymuonsuite/data/dftb_pars/LICENSE
pymuonsuite/data/dftb_pars/__init__.py
pymuonsuite/data/dftb_pars/dftb_pars.py
pymuonsuite/data/dftb_pars/3ob-3-1/args.json
pymuonsuite/data/dftb_pars/3ob-3-1/dftd3.json
pymuonsuite/data/dftb_pars/3ob-3-1/spinpol.json
pymuonsuite/data/dftb_pars/3ob-3-1/wfc.3ob-3-1.hsd
pymuonsuite/data/dftb_pars/3ob-3-1/3ob-3-1/Br-Br.skf
pymuonsuite/data/dftb_pars/3ob-3-1/3ob-3-1/Br-C.skf
pymuonsuite/data/dftb_pars/3ob-3-1/3ob-3-1/Br-Ca.skf
pymuonsuite/data/dftb_pars/3ob-3-1/3ob-3-1/Br-Cl.skf
pymuonsuite/data/dftb_pars/3ob-3-1/3ob-3-1/Br-F.skf
pymuonsuite/data/dftb_pars/3ob-3-1/3ob-3-1/Br-H.skf
pymuonsuite/data/dftb_pars/3ob-3-1/3ob-3-1/Br-I.skf
pymuonsuite/data/dftb_pars/3ob-3-1/3ob-3-1/Br-K.skf
pymuonsuite/data/dftb_pars/3ob-3-1/3ob-3-1/Br-Mg.skf
pymuonsuite/data/dftb_pars/3ob-3-1/3ob-3-1/Br-N.skf
pymuonsuite/data/dftb_pars/3ob-3-1/3ob-3-1/Br-Na.skf
pymuonsuite/data/dftb_pars/3ob-3-1/3ob-3-1/Br-O.skf
pymuonsuite/data/dftb_pars/3ob-3-1/3ob-3-1/Br-P.skf
pymuonsuite/data/dftb_pars/3ob-3-1/3ob-3-1/Br-S.skf
pymuonsuite/data/dftb_pars/3ob-3-1/3ob-3-1/Br-Zn.skf
pymuonsuite/data/dftb_pars/3ob-3-1/3ob-3-1/C-Br.skf
pymuonsuite/data/dftb_pars/3ob-3-1/3ob-3-1/C-C.skf
pymuonsuite/data/dftb_pars/3ob-3-1/3ob-3-1/C-Ca.skf
pymuonsuite/data/dftb_pars/3ob-3-1/3ob-3-1/C-Cl.skf
pymuonsuite/data/dftb_pars/3ob-3-1/3ob-3-1/C-F.skf
pymuonsuite/data/dftb_pars/3ob-3-1/3ob-3-1/C-H.skf
pymuonsuite/data/dftb_pars/3ob-3-1/3ob-3-1/C-I.skf
pymuonsuite/data/dftb_pars/3ob-3-1/3ob-3-1/C-K.skf
pymuonsuite/data/dftb_pars/3ob-3-1/3ob-3-1/C-Mg.skf
pymuonsuite/data/dftb_pars/3ob-3-1/3ob-3-1/C-N.skf
PyMuonSuite-0.3.0.dist-info/LICENSE
PyMuonSuite-0.3.0.dist-info/METADATA
PyMuonSuite-0.3.0.dist-info/WHEEL
PyMuonSuite-0.3.0.dist-info/entry_points.txt
PyMuonSuite-0.3.0.dist-info/top_level.txt
PyMuonSuite-0.3.0.dist-info/RECORD
