Metadata-Version: 2.1
Name: PyMuonSuite
Version: 0.3.0
Summary: A suite of utilities for muon spectroscopy
Author: Simone Sturniolo
Author-email: simone.sturniolo@stfc.ac.uk
License: GPLv3
Classifier: Development Status :: 4 - Beta
Classifier: Intended Audience :: Science/Research
Classifier: Topic :: Scientific/Engineering :: Chemistry
Classifier: Topic :: Scientific/Engineering :: Physics
Classifier: Topic :: Scientific/Engineering :: Information Analysis
Classifier: License :: OSI Approved :: GNU General Public License v3 (GPLv3)
Classifier: Programming Language :: Python :: 3
Requires-Python: >=3.8, <=3.11
License-File: LICENSE
Requires-Dist: numpy
Requires-Dist: scipy
Requires-Dist: ase (>=3.18.1)
Requires-Dist: pyyaml
Requires-Dist: schema
Requires-Dist: spglib (>0.8)
Requires-Dist: soprano (>=0.8.11)
Requires-Dist: parse-fmt (>=0.5)
Provides-Extra: dev
Requires-Dist: pytest ; extra == 'dev'
Requires-Dist: flake8 ; extra == 'dev'
Requires-Dist: black (>=22.3.0) ; extra == 'dev'
Requires-Dist: pre-commit ; extra == 'dev'
Provides-Extra: phonons
Requires-Dist: euphonic ; extra == 'phonons'
